tmtccmd/__init__.py
tmtccmd/com_if.py
tmtccmd/version.py
tmtccmd/cfdp/__init__.py
tmtccmd/cfdp/request.py
tmtccmd/com/__init__.py
tmtccmd/com/dummy.py
tmtccmd/com/qemu.py
tmtccmd/com/ser_utils.py
tmtccmd/com/serial_base.py
tmtccmd/com/serial_cobs.py
tmtccmd/com/serial_dle.py
tmtccmd/com/tcp.py
tmtccmd/com/tcpip_utils.py
tmtccmd/com/udp.py
tmtccmd/com/utils.py
tmtccmd/config/__init__.py
tmtccmd/config/args.py
tmtccmd/config/cfdp.py
tmtccmd/config/com.py
tmtccmd/config/defs.py
tmtccmd/config/globals.py
tmtccmd/config/hook.py
tmtccmd/config/objects.py
tmtccmd/config/prompt.py
tmtccmd/config/tmtc.py
tmtccmd/core/__init__.py
tmtccmd/core/backend_base.py
tmtccmd/core/backend_state.py
tmtccmd/core/base.py
tmtccmd/core/ccsds_backend.py
tmtccmd/core/globals_manager.py
tmtccmd/fsfw/__init__.py
tmtccmd/fsfw/tmtc_printer.py
tmtccmd/gui/__init__.py
tmtccmd/gui/buttons.py
tmtccmd/gui/cmd_select.py
tmtccmd/gui/defs.py
tmtccmd/gui/frontend.py
tmtccmd/gui/worker.py
tmtccmd/logging/__init__.py
tmtccmd/logging/pus.py
tmtccmd/pus/__init__.py
tmtccmd/pus/s11_tc_sched.py
tmtccmd/pus/s11_tc_sched_defs.py
tmtccmd/pus/s17_test.py
tmtccmd/pus/s17_test_defs.py
tmtccmd/pus/s1_verification.py
tmtccmd/pus/s200_fsfw_mode.py
tmtccmd/pus/s200_fsfw_mode_defs.py
tmtccmd/pus/s201_fsfw_health.py
tmtccmd/pus/s201_fsfw_health_defs.py
tmtccmd/pus/s20_fsfw_param.py
tmtccmd/pus/s20_fsfw_param_defs.py
tmtccmd/pus/s3_fsfw_hk.py
tmtccmd/pus/s5_fsfw_event.py
tmtccmd/pus/s5_fsfw_event_defs.py
tmtccmd/pus/s5_satrs_event.py
tmtccmd/pus/s5_satrs_event_defs.py
tmtccmd/pus/s8_fsfw_action.py
tmtccmd/pus/s8_fsfw_action_defs.py
tmtccmd/pus/tc/__init__.py
tmtccmd/pus/tc/s11_tc_sched.py
tmtccmd/pus/tc/s17_test.py
tmtccmd/pus/tc/s200_fsfw_mode.py
tmtccmd/pus/tc/s201_fsfw_health.py
tmtccmd/pus/tc/s20_fsfw_param.py
tmtccmd/pus/tc/s3_fsfw_hk.py
tmtccmd/pus/tc/s5_event.py
tmtccmd/pus/tc/s8_fsfw_action.py
tmtccmd/pus/tm/__init__.py
tmtccmd/pus/tm/s1_verification.py
tmtccmd/pus/tm/s200_fsfw_mode.py
tmtccmd-8.1.1.dist-info/LICENSE-APACHE
tmtccmd-8.1.1.dist-info/LICENSE-MIT
tmtccmd-8.1.1.dist-info/METADATA
tmtccmd-8.1.1.dist-info/NOTICE
tmtccmd-8.1.1.dist-info/WHEEL
tmtccmd-8.1.1.dist-info/top_level.txt
tmtccmd-8.1.1.dist-info/RECORD
