Metadata-Version: 2.2
Name: tmtccmd
Version: 8.1.1
Summary: TMTC Commander Core
Author-email: Robin Mueller <robin.mueller.m@gmail.com>
License: Apache-2.0 or MIT
Project-URL: Homepage, https://github.com/robamu-org/tmtccmd
Keywords: ccsds,ecss,space,communication,packet
Classifier: Development Status :: 5 - Production/Stable
Classifier: License :: OSI Approved :: Apache Software License
Classifier: Natural Language :: English
Classifier: Operating System :: POSIX
Classifier: Operating System :: Microsoft :: Windows
Classifier: Programming Language :: Python :: 3
Classifier: Programming Language :: Python :: 3.8
Classifier: Programming Language :: Python :: 3.9
Classifier: Topic :: Communications
Classifier: Topic :: Software Development :: Libraries
Classifier: Topic :: Software Development :: Libraries :: Python Modules
Classifier: Topic :: Scientific/Engineering
Requires-Python: >=3.9
License-File: LICENSE-APACHE
License-File: LICENSE-MIT
License-File: NOTICE
Requires-Dist: crcmod~=1.7
Requires-Dist: colorama~=0.4.0
Requires-Dist: colorlog~=6.6
Requires-Dist: cobs~=1.2
Requires-Dist: prompt-toolkit~=3.0
Requires-Dist: Deprecated~=1.2
Requires-Dist: pyserial~=3.5
Requires-Dist: dle-encoder~=0.2.3
Requires-Dist: spacepackets<=0.27,>=0.24.0
Requires-Dist: cfdp-py<=0.5,>=0.1.1
Provides-Extra: gui
Requires-Dist: PyQt6~=6.6; extra == "gui"
Provides-Extra: test
Requires-Dist: pyfakefs~=5.7; extra == "test"
Requires-Dist: pytest~=8.3; extra == "test"
